<?xml version="1.0" encoding="UTF-8" ?>
<entry>
    <unicode></unicode>
    <part-of-speech>verb</part-of-speech>
    <romanisations>
        <romanisation system="moellendorff">mutembi</romanisation>
    </romanisations>
    <interpretations>
        <interpretation language="english" references="Moellendorff1892">
            <text>to be able to do</text>
        </interpretation>
    </interpretations>
    <inflexions>
        <inflexion type="future_participle">
            <romanisations>
                <romanisation system="moellendorff">mutere</romanisation>
            </romanisations>
        </inflexion>
    </inflexions>
</entry>